smap_io/__init__.py
smap_io/cli.py
smap_io/download.py
smap_io/grid.py
smap_io/interface.py
smap_io/misc.py
smap_io/reshuffle.py
smap_io/grids/ease36land.nc
smap_io-0.8.dist-info/licenses/AUTHORS.rst
smap_io-0.8.dist-info/licenses/LICENSE.txt
smap_io-0.8.dist-info/METADATA
smap_io-0.8.dist-info/WHEEL
smap_io-0.8.dist-info/entry_points.txt
smap_io-0.8.dist-info/top_level.txt
smap_io-0.8.dist-info/RECORD
