Metadata-Version: 2.4
Name: smap_io
Version: 0.8
Summary: SMAP (Soil Moisture Active Passive) data readers
Home-page: https://github.com/TUW-GEO/smap_io
Author: TU Wien
Author-email: remote.sensing@geo.tuwien.ac.at
License: mit
Project-URL: Documentation, https://smap-io.readthedocs.io/en/latest/
Platform: any
Classifier: Development Status :: 4 - Beta
Classifier: Programming Language :: Python
Requires-Python: >=3.6
License-File: LICENSE.txt
License-File: AUTHORS.rst
Requires-Dist: importlib-metadata; python_version < "3.8"
Requires-Dist: numpy
Requires-Dist: netCDF4
Requires-Dist: h5py
Requires-Dist: pyproj
Requires-Dist: pandas
Requires-Dist: pyresample
Requires-Dist: repurpose>=0.13.2
Requires-Dist: ease-grid
Requires-Dist: pygeobase
Requires-Dist: pygeogrids
Requires-Dist: trollsift==0.2.1
Requires-Dist: pynetcf
Requires-Dist: parse
Provides-Extra: testing
Requires-Dist: pytest-cov; extra == "testing"
Requires-Dist: pytest; extra == "testing"
Requires-Dist: coverage; extra == "testing"
Requires-Dist: yapf; extra == "testing"
Dynamic: license-file
